[
  {
    "slug": "terra-luna",
    "name": "Terra Luna",
    "url": "https://coinmarketcap.com/currencies/terra-luna/",
    "rank": 34,
    "watchlist": 1027418,
    "id": 13,
    "percentage": 1.99,
    "timestamp": "Nov 10, 2022",
    "image": "https://s2.coinmarketcap.com/static/img/coins/200x200/4172.png",
    "difference": -280,
    "degisim": -0.027252783190483326
  },
  {
    "slug": "holo",
    "name": "Holo",
    "url": "https://coinmarketcap.com/currencies/holo/",
    "rank": 100,
    "watchlist": 363058,
    "id": 42,
    "percentage": 0.7,
    "timestamp": "Nov 10, 2022",
    "image": "https://s2.coinmarketcap.com/static/img/coins/200x200/2682.png",
    "difference": -27,
    "degisim": -0.007436828275371979
  },
  {
    "slug": "eos",
    "name": "EOS",
    "url": "https://coinmarketcap.com/currencies/eos/",
    "rank": 51,
    "watchlist": 393149,
    "id": 35,
    "percentage": 0.76,
    "timestamp": "Nov 10, 2022",
    "image": "https://s2.coinmarketcap.com/static/img/coins/200x200/1765.png",
    "difference": -24,
    "degisim": -0.006104555779106649
  },
  {
    "slug": "decentraland",
    "name": "Decentraland",
    "url": "https://coinmarketcap.com/currencies/decentraland/",
    "rank": 47,
    "watchlist": 914145,
    "id": 16,
    "percentage": 1.77,
    "timestamp": "Nov 10, 2022",
    "image": "https://s2.coinmarketcap.com/static/img/coins/200x200/1966.png",
    "difference": -23,
    "degisim": -0.0025160122300072743
  },
  {
    "slug": "nem",
    "name": "Nem",
    "url": "https://coinmarketcap.com/currencies/nem/",
    "rank": 97,
    "watchlist": 168683,
    "id": 67,
    "percentage": 0.33,
    "timestamp": "Nov 10, 2022",
    "image": "https://s2.coinmarketcap.com/static/img/coins/200x200/873.png",
    "difference": -22,
    "degisim": -0.013042215279548028
  }
]