[
  {
    "slug": "usdd",
    "name": "USDD",
    "url": "https://coinmarketcap.com/currencies/usdd/",
    "rank": 60,
    "watchlist": 10851,
    "id": 99,
    "percentage": 0.02,
    "timestamp": "Oct 21, 2022",
    "image": "https://s2.coinmarketcap.com/static/img/coins/200x200/19891.png",
    "difference": -3,
    "degisim": -0.02764722145424385
  },
  {
    "slug": "trueusd",
    "name": "Trueusd",
    "url": "https://coinmarketcap.com/currencies/trueusd/",
    "rank": 58,
    "watchlist": 28098,
    "id": 96,
    "percentage": 0.06,
    "timestamp": "Oct 21, 2022",
    "image": "https://s2.coinmarketcap.com/static/img/coins/200x200/2563.png",
    "difference": -1,
    "degisim": -0.0035589721688376397
  }
]